{
	"name": "Event sheet 1",
	"events": [
		{
			"eventType": "variable",
			"name": "papel",
			"type": "number",
			"initialValue": "0",
			"comment": "",
			"isStatic": false,
			"isConstant": false,
			"sid": 513138937597135
		},
		{
			"eventType": "block",
			"conditions": [
				{
					"id": "on-collision-with-another-object",
					"objectClass": "personagem",
					"sid": 770304680117350,
					"parameters": {
						"object": "bolinha_de_papel"
					}
				}
			],
			"actions": [
				{
					"id": "destroy",
					"objectClass": "bolinha_de_papel",
					"sid": 524083358508840
				},
				{
					"id": "add-to-eventvar",
					"objectClass": "System",
					"sid": 598447585612437,
					"parameters": {
						"variable": "papel",
						"value": "20"
					}
				},
				{
					"id": "play",
					"objectClass": "Áudio",
					"sid": 931086073998528,
					"parameters": {
						"audio-file": "geting-ball-paper",
						"loop": "not-looping",
						"volume": "0",
						"stereo-pan": "0",
						"tag-optional": "\"\""
					}
				}
			],
			"sid": 938138615575312
		},
		{
			"eventType": "block",
			"conditions": [
				{
					"id": "on-key-pressed",
					"objectClass": "Keyboard",
					"sid": 100359334781329,
					"parameters": {
						"key": 38
					}
				}
			],
			"actions": [
				{
					"id": "play",
					"objectClass": "Áudio",
					"sid": 941385996972708,
					"parameters": {
						"audio-file": "cartoon-jump-sound-effect_9TMBNL0N",
						"loop": "not-looping",
						"volume": "0",
						"stereo-pan": "0",
						"tag-optional": "\"\""
					}
				}
			],
			"sid": 890754690196422
		},
		{
			"eventType": "block",
			"conditions": [
				{
					"id": "on-key-pressed",
					"objectClass": "Keyboard",
					"sid": 905557649883754,
					"parameters": {
						"key": 39
					}
				}
			],
			"actions": [
				{
					"id": "set-mirrored",
					"objectClass": "personagem",
					"sid": 631257956592102,
					"parameters": {
						"state": "not-mirrored"
					}
				},
				{
					"id": "set-animation",
					"objectClass": "personagem",
					"sid": 304292364072383,
					"parameters": {
						"animation": "\"ID_WALK\"",
						"from": "beginning"
					}
				},
				{
					"id": "simulate-control",
					"objectClass": "personagem",
					"sid": 891999028107582,
					"behaviorType": "Platform",
					"parameters": {
						"control": "right"
					}
				}
			],
			"sid": 934091499122918
		},
		{
			"eventType": "block",
			"conditions": [
				{
					"id": "on-key-pressed",
					"objectClass": "Keyboard",
					"sid": 588490880748638,
					"parameters": {
						"key": 37
					}
				}
			],
			"actions": [
				{
					"id": "set-animation",
					"objectClass": "personagem",
					"sid": 522202732412894,
					"parameters": {
						"animation": "\"ID_WALK\"",
						"from": "beginning"
					}
				},
				{
					"id": "simulate-control",
					"objectClass": "personagem",
					"sid": 708990361910976,
					"behaviorType": "Platform",
					"parameters": {
						"control": "left"
					}
				},
				{
					"id": "set-mirrored",
					"objectClass": "personagem",
					"sid": 728830019448650,
					"parameters": {
						"state": "mirrored"
					}
				}
			],
			"sid": 844915377101657
		},
		{
			"eventType": "block",
			"conditions": [
				{
					"id": "is-moving",
					"objectClass": "personagem",
					"sid": 394170014200424,
					"behaviorType": "Platform",
					"isInverted": true
				}
			],
			"actions": [
				{
					"id": "set-animation",
					"objectClass": "personagem",
					"sid": 799759781981516,
					"parameters": {
						"animation": "\"ID_IDLE\"",
						"from": "beginning"
					}
				}
			],
			"sid": 879778578158163
		},
		{
			"eventType": "block",
			"conditions": [],
			"actions": [],
			"sid": 650141434001066
		},
		{
			"eventType": "block",
			"conditions": [
				{
					"id": "on-collision-with-another-object",
					"objectClass": "personagem",
					"sid": 875963515707220,
					"parameters": {
						"object": "imageremovebgpreview"
					}
				},
				{
					"id": "compare-eventvar",
					"objectClass": "System",
					"sid": 845535180276130,
					"parameters": {
						"variable": "papel",
						"comparison": 5,
						"value": "100"
					}
				}
			],
			"actions": [
				{
					"id": "set-visible",
					"objectClass": "fundo_txt_mensagem",
					"sid": 372316000983354,
					"parameters": {
						"visibility": "visible"
					}
				},
				{
					"id": "set-visible",
					"objectClass": "txt_mensagem",
					"sid": 417820189257920,
					"parameters": {
						"visibility": "visible"
					}
				},
				{
					"id": "set-visible",
					"objectClass": "Botão",
					"sid": 331110350733320,
					"parameters": {
						"visibility": "visible"
					}
				},
				{
					"id": "play",
					"objectClass": "Áudio",
					"sid": 676367495975053,
					"parameters": {
						"audio-file": "mixkit-game-level-completed-2059",
						"loop": "not-looping",
						"volume": "0",
						"stereo-pan": "0",
						"tag-optional": "\"\""
					}
				},
				{
					"id": "set-eventvar-value",
					"objectClass": "System",
					"sid": 326107704900664,
					"parameters": {
						"variable": "papel",
						"value": "0"
					}
				}
			],
			"sid": 494649444611620
		},
		{
			"eventType": "block",
			"conditions": [
				{
					"id": "on-clicked",
					"objectClass": "Botão",
					"sid": 555333550183402
				}
			],
			"actions": [
				{
					"id": "set-visible",
					"objectClass": "fundo_txt_mensagem",
					"sid": 137204260089486,
					"parameters": {
						"visibility": "invisible"
					}
				},
				{
					"id": "set-visible",
					"objectClass": "txt_mensagem",
					"sid": 522106723254418,
					"parameters": {
						"visibility": "invisible"
					}
				},
				{
					"id": "set-visible",
					"objectClass": "Botão",
					"sid": 124979226542420,
					"parameters": {
						"visibility": "invisible"
					}
				}
			],
			"sid": 253212194256240
		},
		{
			"eventType": "block",
			"conditions": [
				{
					"id": "every-tick",
					"objectClass": "System",
					"sid": 797544000667469
				}
			],
			"actions": [
				{
					"id": "set-progress",
					"objectClass": "BarraDeProgresso",
					"sid": 360355834479628,
					"parameters": {
						"value": "papel"
					}
				}
			],
			"sid": 687079337675259
		}
	],
	"sid": 297663526027258
}